LICENSE.md
gradle_profiler_pttest/__init__.py
gradle_profiler_pttest/analysis_reporter.py
gradle_profiler_pttest/analysis_results.py
gradle_profiler_pttest/app.py
gradle_profiler_pttest/benchmark_parser.py
gradle_profiler_pttest/benchmarks_analyser.py
gradle_profiler_pttest/cli_parser.py
gradle_profiler_pttest/gradle_benchmark.py
gradle_profiler_pttest-0.0.4.dist-info/entry_points.txt
gradle_profiler_pttest-0.0.4.dist-info/LICENSE.md
gradle_profiler_pttest-0.0.4.dist-info/WHEEL
gradle_profiler_pttest-0.0.4.dist-info/METADATA
gradle_profiler_pttest-0.0.4.dist-info/RECORD
