Metadata-Version: 2.1
Name: gradle-profiler-pttest
Version: 0.0.4
Summary: Analyses the outcomes of two Gradle Profiler benchmarks with the Paired T-test statistical technique
Home-page: https://github.com/dotanuki-labs/gradle-profiler-pttest
License: MIT
Author: Ubiratan Soares
Author-email: ubiratan.f.soares@gmail.com
Requires-Python: >=3.8.5,<4.0.0
Classifier: Environment :: Console
Classifier: License :: OSI Approved :: MIT License
Classifier: Operating System :: OS Independent
Classifier: Programming Language :: Python :: 3
Classifier: Programming Language :: Python :: 3.9
Requires-Dist: flake8 (==3.8.4)
Requires-Dist: pingouin (==0.3.8)
Requires-Dist: rich (==9.6.1)
Project-URL: Repository, https://github.com/dotanuki-labs/gradle-profiler-pttest
